cabinet/__init__.py
cabinet/admin.py
cabinet/apps.py
cabinet/base.py
cabinet/base_admin.py
cabinet/ckeditor.py
cabinet/fields.py
cabinet/models.py
cabinet/locale/de/LC_MESSAGES/django.mo
cabinet/locale/de/LC_MESSAGES/django.po
cabinet/locale/fa/LC_MESSAGES/django.mo
cabinet/locale/fa/LC_MESSAGES/django.po
cabinet/locale/ru/LC_MESSAGES/django.mo
cabinet/locale/ru/LC_MESSAGES/django.po
cabinet/locale/tr/LC_MESSAGES/django.mo
cabinet/locale/tr/LC_MESSAGES/django.po
cabinet/management/commands/__init__.py
cabinet/management/commands/archive_cabinet_folder.py
cabinet/migrations/0001_initial.py
cabinet/migrations/0002_auto_20170620_0846.py
cabinet/migrations/0003_file__overwrite.py
cabinet/migrations/0004_auto_20181212_0252.py
cabinet/migrations/0005_auto_20190415_0343.py
cabinet/migrations/0006_alter_folder_unique_together.py
cabinet/migrations/__init__.py
cabinet/static/cabinet/cabinet.css
cabinet/static/cabinet/cabinet.js
cabinet/static/cabinet/ckeditor.js
cabinet/templates/admin/cabinet/cabinet_file_raw_id_widget.html
cabinet/templates/admin/cabinet/file/change_form.html
cabinet/templates/admin/cabinet/file/change_list.html
cabinet/templates/admin/cabinet/folder/change_form.html
django_cabinet-0.18.1.dist-info/METADATA
django_cabinet-0.18.1.dist-info/WHEEL
django_cabinet-0.18.1.dist-info/licenses/LICENSE
django_cabinet-0.18.1.dist-info/RECORD
